{
  "id": "run-003",
  "timestamp": "2026-03-28T00:00:00Z",
  "duration_seconds": 509,
  "status": "success",
  "mode": "unattended",
  "thinker_model": "opus",
  "builder_model": "sonnet",
  "focus": "CLI artifact display integration (AC13)",
  "summary": "Added artifact sections to card/board show commands with conditional display and proper formatting",
  "files_created": [],
  "files_modified": ["src/cli-card.ts", "src/cli-board.ts"],
  "tests": { "passed": 406, "failed": 0, "total": 406 },
  "types_clean": false,
  "build_clean": true,
  "commit": null,
  "acceptance_criteria_met": ["AC13"],
  "acceptance_criteria_progress": "14/15",
  "vault_updates": ["cli-table-formatting-with-printTable.md", "conditional-sections-in-cli-output.md", "cli-json-output-structure.md", "focused-task-with-full-context.md", "formatFileSize-duplication-ok.md"],
  "retry": false,
  "prompt_file": "prompt.md",
  "output_file": "output.md",
  "next_focus": "Search integration to include artifact content (AC14)"
}